{
"title": "Doomsday for Cybercriminals: Data Breach of Major Dark Web Forum",
"category": "Data Breach",
"context": "Major dark web forum for cybercriminals breached, exposing hacker data and operations, disrupting underground markets and aiding law enforcement globally.",
"image_url": "https://www.resecurity.com/uploads/post/592/592.jpg?0b692c71d970d3660aa5b37c25624353",
"sources": [
{
"name": "Resecurity",
"logo_url": "",
"news_url": "https://www.resecurity.com/blog/article/doomsday-for-cybercriminals-data-breach-of-major-dark-web-foru"
}
]
}